README.rst
setup.cfg
setup.py
hyperengine/__init__.py
hyperengine.egg-info/PKG-INFO
hyperengine.egg-info/SOURCES.txt
hyperengine.egg-info/dependency_links.txt
hyperengine.egg-info/requires.txt
hyperengine.egg-info/top_level.txt
hyperengine/base/__init__.py
hyperengine/base/base_io.py
hyperengine/base/logging.py
hyperengine/base/named_dict.py
hyperengine/base/util.py
hyperengine/bayesian/__init__.py
hyperengine/bayesian/kernel.py
hyperengine/bayesian/maximizer.py
hyperengine/bayesian/sampler.py
hyperengine/bayesian/strategy.py
hyperengine/bayesian/utility.py
hyperengine/examples/1_1_hello_word_with_mnist.py
hyperengine/examples/1_2_getting_started_with_tuning.py
hyperengine/examples/1_3_saving_best_models_mnist.py
hyperengine/examples/1_4_fine_tuning_saved_model.py
hyperengine/examples/1_5_learning_curve_prediction.py
hyperengine/examples/1_6_optimizing_regression.py
hyperengine/examples/2_1_cnn_mnist.py
hyperengine/examples/2_2_cnn_cifar.py
hyperengine/examples/2_3_all_conv_net_cifar.py
hyperengine/examples/3_1_lstm_mnist.py
hyperengine/examples/3_2_rnn_sms_spam_detector.py
hyperengine/examples/4_1_word2vec_embedding.py
hyperengine/examples/__init__.py
hyperengine/examples/common.py
hyperengine/impl/__init__.py
hyperengine/impl/tensorflow/__init__.py
hyperengine/impl/tensorflow/tensorflow_model_io.py
hyperengine/impl/tensorflow/tensorflow_runner.py
hyperengine/impl/tensorflow/tensorflow_solver.py
hyperengine/impl/tensorflow/tf_util.py
hyperengine/model/__init__.py
hyperengine/model/base_runner.py
hyperengine/model/base_solver.py
hyperengine/model/curve_predictor.py
hyperengine/model/data_set.py
hyperengine/model/hyper_tuner.py
hyperengine/model/model_io.py
hyperengine/spec/__init__.py
hyperengine/spec/nodes.py
hyperengine/spec/parsed_spec.py
hyperengine/spec/sugar.py