Metadata-Version: 1.0
Name: hyperengine
Version: 0.1.1
Summary: Python library for Bayesian hyper-parameters optimization
Home-page: https://github.com/maxim5/hyper-engine
Author: Maxim Podkolzine
Author-email: maxim.podkolzine@gmail.com
License: Apache 2.0
Keywords: machine learning,hyper-parameters,model selection,bayesian optimization
Platform: UNKNOWN
